shellcolorize/__init__.py
shellcolorize/color.py
shellcolorize-0.2.dist-info/METADATA
shellcolorize-0.2.dist-info/WHEEL
shellcolorize-0.2.dist-info/top_level.txt
shellcolorize-0.2.dist-info/RECORD
