Metadata-Version: 2.1
Name: shellcolorize
Version: 0.2
Summary: A simple library to add ANSI color codes to terminal text
Home-page: https://github.com/serber1990/shell-colorize
Author: Serber1990
Author-email: serber1990@pm.me
Project-URL: Bug Tracker, https://github.com/serber1990/shell-colorize/issues
Project-URL: Documentation, https://github.com/serber1990/shell-colorize
Project-URL: Source Code, https://github.com/serber1990/shell-colorize
Classifier: Programming Language :: Python :: 3
Classifier: Operating System :: OS Independent
Requires-Python: >=3.6
